kiosque/__init__.py
kiosque/__main__.py
kiosque/api/__init__.py
kiosque/api/github.py
kiosque/api/pocket.py
kiosque/api/raindrop.py
kiosque/core/__init__.py
kiosque/core/client.py
kiosque/core/config.py
kiosque/core/website.py
kiosque/tui/__init__.py
kiosque/tui/github.py
kiosque/tui/kiosque.tcss
kiosque/tui/raindrop.py
kiosque/tui/tui.py
kiosque/website/01net.py
kiosque/website/__init__.py
kiosque/website/asahi.py
kiosque/website/aviationweek.py
kiosque/website/courrierinternational.py
kiosque/website/franceculture.py
kiosque/website/francetvinfo.py
kiosque/website/ft.py
kiosque/website/ladepeche.py
kiosque/website/latimes.py
kiosque/website/lefigaro.py
kiosque/website/lemonde.py
kiosque/website/lesechos.py
kiosque/website/letemps.py
kiosque/website/mediapart.py
kiosque/website/mondediplomatique.py
kiosque/website/nationalgeographic.py
kiosque/website/nbcnews.py
kiosque/website/newyorker.py
kiosque/website/nikkei.py
kiosque/website/nytimes.py
kiosque/website/policito.py
kiosque/website/pourlascience.py
kiosque/website/quantamagazine.py
kiosque/website/reporterre.py
kiosque/website/rugbyrama.py
kiosque/website/telerama.py
kiosque/website/theatlantic.py
kiosque/website/theconversation.py
kiosque/website/theguardian.py
kiosque/website/usinenouvelle.py
kiosque/website/washingtonpost.py
kiosque/website/yomiuri.py
kiosque-0.1.0.dist-info/METADATA
kiosque-0.1.0.dist-info/WHEEL
kiosque-0.1.0.dist-info/entry_points.txt
kiosque-0.1.0.dist-info/RECORD
