Metadata-Version: 2.4
Name: kiosque
Version: 0.1.0
Summary: Save newspaper articles in textual format
Author-email: Xavier Olive <git@xoolive.org>
License-Expression: MIT
Classifier: Development Status :: 5 - Production/Stable
Classifier: Intended Audience :: Information Technology
Classifier: License :: OSI Approved :: MIT License
Classifier: Operating System :: MacOS
Classifier: Operating System :: Microsoft :: Windows
Classifier: Operating System :: POSIX :: Linux
Classifier: Programming Language :: Python :: 3
Classifier: Programming Language :: Python :: 3.12
Classifier: Programming Language :: Python :: 3.13
Classifier: Programming Language :: Python :: 3.14
Classifier: Topic :: Software Development :: Libraries
Classifier: Typing :: Typed
Requires-Python: >=3.12
Requires-Dist: appdirs>=1.4.4
Requires-Dist: bs4>=0.0.2
Requires-Dist: click>=8.1.7
Requires-Dist: httpx-socks>=0.9.2
Requires-Dist: httpx>=0.27.2
Requires-Dist: lxml>=5.3.0
Requires-Dist: pydantic>=2.11.5
Requires-Dist: pypandoc>=1.13
Requires-Dist: pyperclip>=1.9.0
Requires-Dist: stamina>=24.3.0
Requires-Dist: textual>=0.81.0
